infi.app_repo-1.3.1-py3.7-nspkg.pth
infi/app_repo/__init__.py
infi/app_repo/__version__.py
infi/app_repo/config.py
infi/app_repo/errors.py
infi/app_repo/filename_parser.py
infi/app_repo/ftpserver.py
infi/app_repo/gpg_batch_file
infi/app_repo/install.py
infi/app_repo/mock.py
infi/app_repo/persistent_dict.py
infi/app_repo/service.py
infi/app_repo/sync.py
infi/app_repo/systemd.py
infi/app_repo/utils.py
infi/app_repo/indexers/__init__.py
infi/app_repo/indexers/apt.py
infi/app_repo/indexers/base.py
infi/app_repo/indexers/pypi.py
infi/app_repo/indexers/python.py
infi/app_repo/indexers/vmware_studio_updates.py
infi/app_repo/indexers/wget.py
infi/app_repo/indexers/yum.py
infi/app_repo/scripts/__init__.py
infi/app_repo/scripts/extended.py
infi/app_repo/scripts/simple.py
infi/app_repo/webserver/__init__.py
infi/app_repo/webserver/auth.py
infi/app_repo/webserver/wsgi.py
infi/app_repo/webserver/static/css/apprepo.css
infi/app_repo/webserver/static/css/bootstrap-responsive.css
infi/app_repo/webserver/static/css/bootstrap-responsive.min.css
infi/app_repo/webserver/static/css/bootstrap-theme.css
infi/app_repo/webserver/static/css/bootstrap-theme.min.css
infi/app_repo/webserver/static/css/bootstrap.css
infi/app_repo/webserver/static/css/bootstrap.min.css
infi/app_repo/webserver/static/css/bootstrap.vertical-tabs.min.css
infi/app_repo/webserver/static/css/jquery.dataTables.min.css
infi/app_repo/webserver/static/css/opensans.css
infi/app_repo/webserver/static/css/simple-sidebar.css
infi/app_repo/webserver/static/img/favicon.ico
infi/app_repo/webserver/static/img/glyphicons-halflings-white.png
infi/app_repo/webserver/static/img/glyphicons-halflings.png
infi/app_repo/webserver/static/img/logo-aix.png
infi/app_repo/webserver/static/img/logo-centos.png
infi/app_repo/webserver/static/img/logo-docker.png
infi/app_repo/webserver/static/img/logo-oracle.png
infi/app_repo/webserver/static/img/logo-python-docs.png
infi/app_repo/webserver/static/img/logo-python.png
infi.app_repo-1.3.1.dist-info/LICENSE
infi.app_repo-1.3.1.dist-info/METADATA
infi.app_repo-1.3.1.dist-info/WHEEL
infi.app_repo-1.3.1.dist-info/entry_points.txt
infi.app_repo-1.3.1.dist-info/namespace_packages.txt
infi.app_repo-1.3.1.dist-info/top_level.txt
infi.app_repo-1.3.1.dist-info/RECORD
