Metadata-Version: 2.1
Name: infi.app-repo
Version: 1.3.1
Summary: A user-friendly RPM/DEP repository
Home-page: https://github.com/Infinidat/infi.app_repo
Author: Arnon Yaari
Author-email: arnony@infinidat.com
License: BSD
Platform: UNKNOWN
Classifier: Intended Audience :: Developers
Classifier: Intended Audience :: System Administrators
Classifier: License :: OSI Approved :: BSD License
Classifier: Operating System :: OS Independent
Classifier: Programming Language :: Python
Classifier: Topic :: Software Development :: Libraries :: Python Modules
Requires-Dist: docopt
Requires-Dist: Flask
Requires-Dist: Flask-AutoIndex
Requires-Dist: Flask-Cors
Requires-Dist: gevent
Requires-Dist: httpie
Requires-Dist: infi.docopt-completion
Requires-Dist: infi.execute
Requires-Dist: infi.gevent-utils
Requires-Dist: infi.logging
Requires-Dist: infi.pyutils
Requires-Dist: infi.rpc
Requires-Dist: infi.traceback
Requires-Dist: ipython (<6)
Requires-Dist: pyftpdlib
Requires-Dist: Pygments
Requires-Dist: pysendfile
Requires-Dist: python-dateutil
Requires-Dist: requests
Requires-Dist: schematics (<1.1.1)
Requires-Dist: setuptools
Requires-Dist: waiting
Requires-Dist: zc.buildout
